Workbook

Sheet CSA 덤프 v1.0
A1: Seq. | B1: 기출 | C1: Q 번호 | D1: 아리 | E1: 썸머 | F1: 에릭 | G1: 구분 | H1: 본문 | I1: 비고 | J1: 확인필요 | K1: 검수자 | L1: 검수일자
A2: 1 | B2: 2 | C2: 1 | G2: 문제 | H2: NO.1 Which ServiceNow capability allows you to provide knowledge articles, via a conversational messaging interface?
A3: 2 | B3: =B2 -> 2 | C3: =C2 -> 1 | F3: =F2 -> 0 | G3: 보기 | H3: (A). Agent Assist
A4: 3 | B4: =B3 -> 2 | C4: =C3 -> 1 | F4: =F3 -> 0 | G4: 보기 | H4: (B). Virtual Agent
A5: 4 | B5: =B4 -> 2 | C5: =C4 -> 1 | F5: =F4 -> 0 | G5: 보기 | H5: (C). Now Messenger
A6: 5 | B6: =B5 -> 2 | C6: =C5 -> 1 | F6: =F5 -> 0 | G6: 보기 | H6: (D). Connect Agent
A7: 6 | B7: =B6 -> 2 | C7: =C6 -> 1 | F7: =F6 -> 0 | G7: 답 | H7: B
A8: 7 | B8: =B7 -> 2 | C8: =C7 -> 1 | F8: =F7 -> 0
A9: 8 | B9: 1 | C9: 2 | G9: 문제 | H9: NO.2 What feature do you use to specify which users are able to access a Service Catalog Item?
A10: 9 | B10: =B9 -> 1 | C10: =C9 -> 2 | F10: =F9 -> 0 | G10: 보기 | H10: (A). Can Read Role
A11: 10 | B11: =B10 -> 1 | C11: =C10 -> 2 | F11: =F10 -> 0 | G11: 보기 | H11: (B). Catalog User Role
A12: 11 | B12: =B11 -> 1 | C12: =C11 -> 2 | F12: =F11 -> 0 | G12: 보기 | H12: (C). Can Order Tab
A13: 12 | B13: =B12 -> 1 | C13: =C12 -> 2 | F13: =F12 -> 0 | G13: 보기 | H13: (D). User Criteria
A14: 13 | B14: =B13 -> 1 | C14: =C13 -> 2 | F14: =F13 -> 0 | G14: 답 | H14: D
A15: 14 | B15: =B14 -> 1 | C15: =C14 -> 2 | F15: =F14 -> 0
A16: 15 | B16: 0 | C16: 3 | G16: 문제 | H16: NO.3 How are Workflows moved between instances?
A17: 16 | B17: =B16 -> 0 | C17: =C16 -> 3 | F17: =F16 -> 0 | G17: 보기 | H17: (A). Workflows are moved using Update Sets
A18: 17 | B18: =B17 -> 0 | C18: =C17 -> 3 | F18: =F17 -> 0 | G18: 보기 | H18: (B). Workflows are moved using Transform Maps
A19: 18 | B19: =B18 -> 0 | C19: =C18 -> 3 | F19: =F18 -> 0 | G19: 보기 | H19: (C). Workflows are moved using Application Sets
A20: 19 | B20: =B19 -> 0 | C20: =C19 -> 3 | F20: =F19 -> 0 | G20: 보기 | H20: (D). Workflows cannot be moved between instances
A21: 20 | B21: =B20 -> 0 | C21: =C20 -> 3 | F21: =F20 -> 0 | G21: 답 | H21: A
A22: 21 | B22: =B21 -> 0 | C22: =C21 -> 3 | F22: =F21 -> 0
A23: 22 | B23: 2 | C23: 4 | G23: 문제 | H23: NO.4 Which role can manage multiple knowledge bases?
A24: 23 | B24: =B23 -> 2 | C24: =C23 -> 4 | F24: =F23 -> 0 | G24: 보기 | H24: (A). knowledge_base_admin
A25: 24 | B25: =B24 -> 2 | C25: =C24 -> 4 | F25: =F24 -> 0 | G25: 보기 | H25: (B). kb_admin
A26: 25 | B26: =B25 -> 2 | C26: =C25 -> 4 | F26: =F25 -> 0 | G26: 보기 | H26: (C). sn_kb_admin
A27: 26 | B27: =B26 -> 2 | C27: =C26 -> 4 | F27: =F26 -> 0 | G27: 보기 | H27: (D). knowledge_admin
A28: 27 | B28: =B27 -> 2 | C28: =C27 -> 4 | F28: =F27 -> 0 | G28: 답 | H28: D
A29: 28 | B29: =B28 -> 2 | C29: =C28 -> 4 | F29: =F28 -> 0
A30: 29 | B30: 0 | C30: 5 | G30: 문제 | H30: NO.5 Reports can be created from which different places in the platform? (Choose two.)
A31: 30 | B31: =B30 -> 0 | C31: =C30 -> 5 | F31: =F30 -> 0 | G31: 보기 | H31: (A). List column heading
A32: 31 | B32: =B31 -> 0 | C32: =C31 -> 5 | F32: =F31 -> 0 | G32: 보기 | H32: (B). Metrics module
A33: 32 | B33: =B32 -> 0 | C33: =C32 -> 5 | F33: =F32 -> 0 | G33: 보기 | H33: (C). Statistics module
A34: 33 | B34: =B33 -> 0 | C34: =C33 -> 5 | F34: =F33 -> 0 | G34: 보기 | H34: (D). View / Run module
A35: 34 | B35: =B34 -> 0 | C35: =C34 -> 5 | F35: =F34 -> 0 | G35: 답 | H35: AD
A36: 35 | B36: =B35 -> 0 | C36: =C35 -> 5 | F36: =F35 -> 0
A37: 36 | B37: 0 | C37: 6 | G37: 문제 | H37: NO.6 What refers to an application or system that accesses a remote service or another computer system, known as a server?
A38: 37 | B38: =B37 -> 0 | C38: =C37 -> 6 | F38: =F37 -> 0 | G38: 보기 | H38: (A). Server
A39: 38 | B39: =B38 -> 0 | C39: =C38 -> 6 | F39: =F38 -> 0 | G39: 보기 | H39: (B). Client
A40: 39 | B40: =B39 -> 0 | C40: =C39 -> 6 | F40: =F39 -> 0 | G40: 보기 | H40: (C). Script
A41: 40 | B41: =B40 -> 0 | C41: =C40 -> 6 | F41: =F40 -> 0 | G41: 보기 | H41: (D). Policies
A42: 41 | B42: =B41 -> 0 | C42: =C41 -> 6 | F42: =F41 -> 0 | G42: 답 | H42: B
A43: 42 | B43: =B42 -> 0 | C43: =C42 -> 6 | F43: =F42 -> 0
A44: 43 | B44: 0 | C44: 7 | G44: 문제 | H44: NO.7 What are the four knowledge workflows available in the ServiceNow base instance?
A45: 44 | B45: =B44 -> 0 | C45: =C44 -> 7 | F45: =F44 -> 0 | G45: 보기 | H45: (A). Approval publish: Request approval from a manager of the knowledge base before moving the article it the publish state
A46: 45 | B46: =B45 -> 0 | C46: =C45 -> 7 | F46: =F45 -> 0 | G46: 보기 | H46: (B). Instant Publish: Immediately publishes a draft article without requiring an approval
A47: 46 | B47: =B46 -> 0 | C47: =C46 -> 7 | F47: =F46 -> 0 | G47: 보기 | H47: (C). Instant Retire: Immediately retires a published article without requiring an approval
A48: 47 | B48: =B47 -> 0 | C48: =C47 -> 7 | F48: =F47 -> 0 | G48: 보기 | H48: (D). Retire Knowledge: Moves a knowledge article to the retired state.
A49: 48 | B49: =B48 -> 0 | C49: =C48 -> 7 | F49: =F48 -> 0 | G49: 답 | H49: A
A50: 49 | B50: =B49 -> 0 | C50: =C49 -> 7 | F50: =F49 -> 0
A51: 50 | B51: 0 | C51: 8 | G51: 문제 | H51: NO.8 Which statement is true about business rules?
A52: 51 | B52: =B51 -> 0 | C52: =C51 -> 8 | F52: =F51 -> 0 | G52: 보기 | H52: (A). A business rule must run before a database action occurs
A53: 52 | B53: =B52 -> 0 | C53: =C52 -> 8 | F53: =F52 -> 0 | G53: 보기 | H53: (B). A business rule can be a piece of Javascript
A54: 53 | B54: =B53 -> 0 | C54: =C53 -> 8 | F54: =F53 -> 0 | G54: 보기 | H54: (C). A business rule must not run before a database action occurs
A55: 54 | B55: =B54 -> 0 | C55: =C54 -> 8 | F55: =F54 -> 0 | G55: 보기 | H55: (D). A business rule monitors fields on a form
A56: 55 | B56: =B55 -> 0 | C56: =C55 -> 8 | F56: =F55 -> 0 | G56: 답 | H56: B
A57: 56 | B57: =B56 -> 0 | C57: =C56 -> 8 | F57: =F56 -> 0
A58: 57 | B58: 0 | C58: 9 | G58: 문제 | H58: NO.9 What is the purpose of the Event Registry?
A59: 58 | B59: =B58 -> 0 | C59: =C58 -> 9 | F59: =F58 -> 0 | G59: 보기 | H59: (A). The Event Registry lists all Events that have successfully completed within a 24-hour period
A60: 59 | B60: =B59 -> 0 | C60: =C59 -> 9 | F60: =F59 -> 0 | G60: 보기 | H60: (B). The Event Registry is a list of all Events that originate through an integration
A61: 60 | B61: =B60 -> 0 | C61: =C60 -> 9 | F61: =F60 -> 0 | G61: 보기 | H61: (C). The Event Registry is a module that provides Event definitions
A62: 61 | B62: =B61 -> 0 | C62: =C61 -> 9 | F62: =F61 -> 0 | G62: 보기 | H62: (D). The Event Registry is a list of all Events that have successfully completed after being Invoked by a script
A63: 62 | B63: =B62 -> 0 | C63: =C62 -> 9 | F63: =F62 -> 0 | G63: 답 | H63: C
A64: 63 | B64: =B63 -> 0 | C64: =C63 -> 9 | F64: =F63 -> 0
A65: 64 | B65: 0 | C65: 10 | G65: 문제 | H65: NO.10 What is the name of the conversational bot platform that provides assistance to help users obtain information, make decisions, and perform common tasks?
A66: 65 | B66: =B64 -> 0 | C66: =C64 -> 9 | F66: =F64 -> 0 | G66: 보기 | H66: (A). Answer Agent
H67: (B). Live Feed
H68: (C). Virtual Agent
H69: (D). Connect Chat
A70: 66 | B70: =B65 -> 0 | C70: =C65 -> 10 | F70: =F65 -> 0 | G70: 답 | H70: C
A71: 67 | B71: =B66 -> 0 | C71: =C66 -> 9 | F71: =F66 -> 0
A72: 68 | B72: 2 | C72: 11 | G72: 문제 | H72: NO.11 User records are stored in which table?
A73: 69 | B73: =B72 -> 2 | C73: =C72 -> 11 | F73: =F72 -> 0 | G73: 보기 | H73: (A). User [sys_user]
A74: 70 | B74: =B73 -> 2 | C74: =C73 -> 11 | F74: =F73 -> 0 | G74: 보기 | H74: (B). User [sn_user]
A75: 71 | B75: =B74 -> 2 | C75: =C74 -> 11 | F75: =F74 -> 0 | G75: 보기 | H75: (C). User [u_sys_user]
A76: 72 | B76: =B75 -> 2 | C76: =C75 -> 11 | F76: =F75 -> 0 | G76: 보기 | H76: (D). User [s_user]
A77: 73 | B77: =B76 -> 2 | C77: =C76 -> 11 | F77: =F76 -> 0 | G77: 답 | H77: A
A78: 74 | B78: =B77 -> 2 | C78: =C77 -> 11 | F78: =F77 -> 0
A79: 75 | B79: 0 | C79: 12 | G79: 문제 | H79: NO.12 Which tool should be used to populate commonly used fields in a form?
A80: 76 | B80: =B79 -> 0 | C80: =C79 -> 12 | F80: =F79 -> 0 | G80: 보기 | H80: (A). Template
A81: 77 | B81: =B80 -> 0 | C81: =C80 -> 12 | F81: =F80 -> 0 | G81: 보기 | H81: (B). Reference Qualifier
A82: 78 | B82: =B81 -> 0 | C82: =C81 -> 12 | F82: =F81 -> 0 | G82: 보기 | H82: (C). Formatter
A83: 79 | B83: =B82 -> 0 | C83: =C82 -> 12 | F83: =F82 -> 0 | G83: 보기 | H83: (D). Assignment Rule
A84: 80 | B84: =B83 -> 0 | C84: =C83 -> 12 | F84: =F83 -> 0 | G84: 답 | H84: A
A85: 81 | B85: =B84 -> 0 | C85: =C84 -> 12 | F85: =F84 -> 0
A86: 82 | B86: 0 | C86: 13 | G86: 문제 | H86: NO.13 Which one of the following statements describes a characteristic of role assignment?
A87: 83 | B87: =B86 -> 0 | C87: =C86 -> 13 | F87: =F86 -> 0 | G87: 보기 | H87: (A). Roles can contain other roles, when you are assigned a role, you inherit all the roles within that role
A88: 84 | B88: =B87 -> 0 | C88: =C87 -> 13 | F88: =F87 -> 0 | G88: 보기 | H88: (B). Users can click on the Personalize Role feature to try different roles
A89: 85 | B89: =B88 -> 0 | C89: =C88 -> 13 | F89: =F88 -> 0 | G89: 보기 | H89: (C). A role is granted to a user by the System Administrator
A90: 86 | B90: =B89 -> 0 | C90: =C89 -> 13 | F90: =F89 -> 0 | G90: 보기 | H90: (D). Each user has a role in the ServiceNow platform
A91: 87 | B91: =B90 -> 0 | C91: =C90 -> 13 | F91: =F90 -> 0 | G91: 답 | H91: A
A92: 88 | B92: =B91 -> 0 | C92: =C91 -> 13 | F92: =F91 -> 0
A93: 89 | B93: 0 | C93: 14 | G93: 문제 | H93: NO.14 When does the Submit button appear on a form?
A94: 90 | B94: =B93 -> 0 | C94: =C93 -> 14 | F94: =F93 -> 0 | G94: 보기 | H94: (A). When saving an old record
A95: 91 | B95: =B94 -> 0 | C95: =C94 -> 14 | F95: =F94 -> 0 | G95: 보기 | H95: (B). When creating a new record
A96: 92 | B96: =B95 -> 0 | C96: =C95 -> 14 | F96: =F95 -> 0 | G96: 보기 | H96: (C). When changing the reference field in an existing record
A97: 93 | B97: =B96 -> 0 | C97: =C96 -> 14 | F97: =F96 -> 0 | G97: 보기 | H97: (D). When updating an existing record
A98: 94 | B98: =B97 -> 0 | C98: =C97 -> 14 | F98: =F97 -> 0 | G98: 답 | H98: B
A99: 95 | B99: =B98 -> 0 | C99: =C98 -> 14 | F99: =F98 -> 0
A100: 96 | B100: 0 | C100: 15 | G100: 문제 | H100: NO.15 Which tool is used to define relationships between fields in an import set table and a target table?
...

Sheet 문제풀이
A1: Seq. | B1: 기출 | C1: Q 번호 | D1: 1차 | E1: 2차 | F1: 3차 | G1: 4차 | H1: 구분 | I1: 본문 | J1: ="3차 "&ROUND(COUNTIF(J2:J1795,TRUE)/SUM(COUNTIF(J3:J1795,TRUE),COUNTIF(J3:J1795,FALSE))*100,2)&"%" -> 3차 71.61% | K1: ="3차 "&ROUND(COUNTIF(K2:K1795,TRUE)/SUM(COUNTIF(K3:K1795,TRUE),COUNTIF(K3:K1795,FALSE))*100,2)&"%" -> 3차 72.97% | L1: ="3차 "&ROUND(COUNTIF(L2:L1795,TRUE)/SUM(COUNTIF(L3:L1795,TRUE),COUNTIF(L3:L1795,FALSE))*100,2)&"%" -> 3차 84.21% | M1: ="4차 "&ROUND(COUNTIF(M2:M1795,TRUE)/SUM(COUNTIF(M3:M1795,TRUE),COUNTIF(M3:M1795,FALSE))*100,2)&"%" -> 4차 66.67% | N1: 오답 수
A2: 1 | B2: 2 | C2: 1 | H2: ='CSA 덤프 v1.0'!G2 -> 문제 | I2: ='CSA 덤프 v1.0'!H2 -> NO.1 Which ServiceNow capability allows you to provide knowledge articles, via a conversational messaging interface?
A3: 2 | B3: =B2 -> 2 | C3: =C2 -> 1 | H3: ='CSA 덤프 v1.0'!G3 -> 보기 | I3: ='CSA 덤프 v1.0'!H3 -> (A). Agent Assist
A4: 3 | B4: =B3 -> 2 | C4: =C3 -> 1 | H4: ='CSA 덤프 v1.0'!G4 -> 보기 | I4: ='CSA 덤프 v1.0'!H4 -> (B). Virtual Agent
A5: 4 | B5: =B4 -> 2 | C5: =C4 -> 1 | H5: ='CSA 덤프 v1.0'!G5 -> 보기 | I5: ='CSA 덤프 v1.0'!H5 -> (C). Now Messenger
A6: 5 | B6: =B5 -> 2 | C6: =C5 -> 1 | H6: ='CSA 덤프 v1.0'!G6 -> 보기 | I6: ='CSA 덤프 v1.0'!H6 -> (D). Connect Agent
A7: 6 | B7: =B6 -> 2 | C7: =C6 -> 1 | D7: b | H7: ='CSA 덤프 v1.0'!G7 -> 답 | I7: b | J7: =IF(ISBLANK(D7),"",D7=$I7) -> TRUE | K7: =IF(ISBLANK(E7),"",E7=$I7) | L7: =IF(ISBLANK(F7),"",F7=$I7) | M7: =IF(ISBLANK(G7),"",G7=$I7) | N7: =COUNTIF(J7:M7,FALSE) -> 0
A8: 7 | B8: =B7 -> 2 | C8: =C7 -> 1 | H8: ='CSA 덤프 v1.0'!G8 -> 0 | I8: ='CSA 덤프 v1.0'!H8 -> 0
A9: 8 | B9: 1 | C9: 2 | H9: ='CSA 덤프 v1.0'!G9 -> 문제 | I9: ='CSA 덤프 v1.0'!H9 -> NO.2 What feature do you use to specify which users are able to access a Service Catalog Item?
A10: 9 | B10: =B9 -> 1 | C10: =C9 -> 2 | H10: ='CSA 덤프 v1.0'!G10 -> 보기 | I10: ='CSA 덤프 v1.0'!H10 -> (A). Can Read Role
A11: 10 | B11: =B10 -> 1 | C11: =C10 -> 2 | H11: ='CSA 덤프 v1.0'!G11 -> 보기 | I11: ='CSA 덤프 v1.0'!H11 -> (B). Catalog User Role
A12: 11 | B12: =B11 -> 1 | C12: =C11 -> 2 | H12: ='CSA 덤프 v1.0'!G12 -> 보기 | I12: ='CSA 덤프 v1.0'!H12 -> (C). Can Order Tab
A13: 12 | B13: =B12 -> 1 | C13: =C12 -> 2 | H13: ='CSA 덤프 v1.0'!G13 -> 보기 | I13: ='CSA 덤프 v1.0'!H13 -> (D). User Criteria
A14: 13 | B14: =B13 -> 1 | C14: =C13 -> 2 | D14: d | H14: ='CSA 덤프 v1.0'!G14 -> 답 | I14: ='CSA 덤프 v1.0'!H14 -> D | J14: =IF(ISBLANK(D14),"",D14=$I14) -> TRUE | K14: =IF(ISBLANK(E14),"",E14=$I14) | L14: =IF(ISBLANK(F14),"",F14=$I14) | M14: =IF(ISBLANK(G14),"",G14=$I14) | N14: =COUNTIF(J14:M14,FALSE) -> 0
A15: 14 | B15: =B14 -> 1 | C15: =C14 -> 2 | H15: ='CSA 덤프 v1.0'!G15 -> 0 | I15: ='CSA 덤프 v1.0'!H15 -> 0
A16: 15 | B16: 0 | C16: 3 | H16: ='CSA 덤프 v1.0'!G16 -> 문제 | I16: ='CSA 덤프 v1.0'!H16 -> NO.3 How are Workflows moved between instances?
A17: 16 | B17: =B16 -> 0 | C17: =C16 -> 3 | H17: ='CSA 덤프 v1.0'!G17 -> 보기 | I17: ='CSA 덤프 v1.0'!H17 -> (A). Workflows are moved using Update Sets
A18: 17 | B18: =B17 -> 0 | C18: =C17 -> 3 | H18: ='CSA 덤프 v1.0'!G18 -> 보기 | I18: ='CSA 덤프 v1.0'!H18 -> (B). Workflows are moved using Transform Maps
A19: 18 | B19: =B18 -> 0 | C19: =C18 -> 3 | H19: ='CSA 덤프 v1.0'!G19 -> 보기 | I19: ='CSA 덤프 v1.0'!H19 -> (C). Workflows are moved using Application Sets
A20: 19 | B20: =B19 -> 0 | C20: =C19 -> 3 | H20: ='CSA 덤프 v1.0'!G20 -> 보기 | I20: ='CSA 덤프 v1.0'!H20 -> (D). Workflows cannot be moved between instances
A21: 20 | B21: =B20 -> 0 | C21: =C20 -> 3 | D21: a | H21: ='CSA 덤프 v1.0'!G21 -> 답 | I21: ='CSA 덤프 v1.0'!H21 -> A | J21: =IF(ISBLANK(D21),"",D21=$I21) -> TRUE | K21: =IF(ISBLANK(E21),"",E21=$I21) | L21: =IF(ISBLANK(F21),"",F21=$I21) | M21: =IF(ISBLANK(G21),"",G21=$I21) | N21: =COUNTIF(J21:M21,FALSE) -> 0
A22: 21 | B22: =B21 -> 0 | C22: =C21 -> 3 | H22: ='CSA 덤프 v1.0'!G22 -> 0 | I22: ='CSA 덤프 v1.0'!H22 -> 0
A23: 22 | B23: 2 | C23: 4 | H23: ='CSA 덤프 v1.0'!G23 -> 문제 | I23: ='CSA 덤프 v1.0'!H23 -> NO.4 Which role can manage multiple knowledge bases?
A24: 23 | B24: =B23 -> 2 | C24: =C23 -> 4 | H24: ='CSA 덤프 v1.0'!G24 -> 보기 | I24: ='CSA 덤프 v1.0'!H24 -> (A). knowledge_base_admin
A25: 24 | B25: =B24 -> 2 | C25: =C24 -> 4 | H25: ='CSA 덤프 v1.0'!G25 -> 보기 | I25: ='CSA 덤프 v1.0'!H25 -> (B). kb_admin
A26: 25 | B26: =B25 -> 2 | C26: =C25 -> 4 | H26: ='CSA 덤프 v1.0'!G26 -> 보기 | I26: ='CSA 덤프 v1.0'!H26 -> (C). sn_kb_admin
A27: 26 | B27: =B26 -> 2 | C27: =C26 -> 4 | H27: ='CSA 덤프 v1.0'!G27 -> 보기 | I27: ='CSA 덤프 v1.0'!H27 -> (D). knowledge_admin
A28: 27 | B28: =B27 -> 2 | C28: =C27 -> 4 | D28: d | H28: ='CSA 덤프 v1.0'!G28 -> 답 | I28: ='CSA 덤프 v1.0'!H28 -> D | J28: =IF(ISBLANK(D28),"",D28=$I28) -> TRUE | K28: =IF(ISBLANK(E28),"",E28=$I28) | L28: =IF(ISBLANK(F28),"",F28=$I28) | M28: =IF(ISBLANK(G28),"",G28=$I28) | N28: =COUNTIF(J28:M28,FALSE) -> 0
A29: 28 | B29: =B28 -> 2 | C29: =C28 -> 4 | H29: ='CSA 덤프 v1.0'!G29 -> 0 | I29: ='CSA 덤프 v1.0'!H29 -> 0
A30: 29 | B30: 0 | C30: 5 | H30: ='CSA 덤프 v1.0'!G30 -> 문제 | I30: ='CSA 덤프 v1.0'!H30 -> NO.5 Reports can be created from which different places in the platform? (Choose two.)
A31: 30 | B31: =B30 -> 0 | C31: =C30 -> 5 | H31: ='CSA 덤프 v1.0'!G31 -> 보기 | I31: ='CSA 덤프 v1.0'!H31 -> (A). List column heading
A32: 31 | B32: =B31 -> 0 | C32: =C31 -> 5 | H32: ='CSA 덤프 v1.0'!G32 -> 보기 | I32: ='CSA 덤프 v1.0'!H32 -> (B). Metrics module
A33: 32 | B33: =B32 -> 0 | C33: =C32 -> 5 | H33: ='CSA 덤프 v1.0'!G33 -> 보기 | I33: ='CSA 덤프 v1.0'!H33 -> (C). Statistics module
A34: 33 | B34: =B33 -> 0 | C34: =C33 -> 5 | H34: ='CSA 덤프 v1.0'!G34 -> 보기 | I34: ='CSA 덤프 v1.0'!H34 -> (D). View / Run module
A35: 34 | B35: =B34 -> 0 | C35: =C34 -> 5 | D35: ad | H35: ='CSA 덤프 v1.0'!G35 -> 답 | I35: ='CSA 덤프 v1.0'!H35 -> AD | J35: =IF(ISBLANK(D35),"",D35=$I35) -> TRUE | K35: =IF(ISBLANK(E35),"",E35=$I35) | L35: =IF(ISBLANK(F35),"",F35=$I35) | M35: =IF(ISBLANK(G35),"",G35=$I35) | N35: =COUNTIF(J35:M35,FALSE) -> 0
A36: 35 | B36: =B35 -> 0 | C36: =C35 -> 5 | H36: ='CSA 덤프 v1.0'!G36 -> 0 | I36: ='CSA 덤프 v1.0'!H36 -> 0
A37: 36 | B37: 0 | C37: 6 | H37: ='CSA 덤프 v1.0'!G37 -> 문제 | I37: ='CSA 덤프 v1.0'!H37 -> NO.6 What refers to an application or system that accesses a remote service or another computer system, known as a server?
A38: 37 | B38: =B37 -> 0 | C38: =C37 -> 6 | H38: ='CSA 덤프 v1.0'!G38 -> 보기 | I38: ='CSA 덤프 v1.0'!H38 -> (A). Server
A39: 38 | B39: =B38 -> 0 | C39: =C38 -> 6 | H39: ='CSA 덤프 v1.0'!G39 -> 보기 | I39: ='CSA 덤프 v1.0'!H39 -> (B). Client
A40: 39 | B40: =B39 -> 0 | C40: =C39 -> 6 | H40: ='CSA 덤프 v1.0'!G40 -> 보기 | I40: ='CSA 덤프 v1.0'!H40 -> (C). Script
A41: 40 | B41: =B40 -> 0 | C41: =C40 -> 6 | H41: ='CSA 덤프 v1.0'!G41 -> 보기 | I41: ='CSA 덤프 v1.0'!H41 -> (D). Policies
A42: 41 | B42: =B41 -> 0 | C42: =C41 -> 6 | D42: b | H42: ='CSA 덤프 v1.0'!G42 -> 답 | I42: ='CSA 덤프 v1.0'!H42 -> B | J42: =IF(ISBLANK(D42),"",D42=$I42) -> TRUE | K42: =IF(ISBLANK(E42),"",E42=$I42) | L42: =IF(ISBLANK(F42),"",F42=$I42) | M42: =IF(ISBLANK(G42),"",G42=$I42) | N42: =COUNTIF(J42:M42,FALSE) -> 0
A43: 42 | B43: =B42 -> 0 | C43: =C42 -> 6 | H43: ='CSA 덤프 v1.0'!G43 -> 0 | I43: ='CSA 덤프 v1.0'!H43 -> 0
A44: 43 | B44: 0 | C44: 7 | H44: ='CSA 덤프 v1.0'!G44 -> 문제 | I44: ='CSA 덤프 v1.0'!H44 -> NO.7 What are the four knowledge workflows available in the ServiceNow base instance?
A45: 44 | B45: =B44 -> 0 | C45: =C44 -> 7 | H45: ='CSA 덤프 v1.0'!G45 -> 보기 | I45: ='CSA 덤프 v1.0'!H45 -> (A). Approval publish: Request approval from a manager of the knowledge base before moving the article it the publish state | P45: B각 workflow에 대한 설명이 부족하기 떄문에 정답이 아닌 것으로 추정
A46: 45 | B46: =B45 -> 0 | C46: =C45 -> 7 | H46: ='CSA 덤프 v1.0'!G46 -> 보기 | I46: ='CSA 덤프 v1.0'!H46 -> (B). Instant Publish: Immediately publishes a draft article without requiring an approval | P46: Immediately publishes a draft article without requiring an approval, or publishes on the scheduled publish date if set to publish later.
A47: 46 | B47: =B46 -> 0 | C47: =C46 -> 7 | H47: ='CSA 덤프 v1.0'!G47 -> 보기 | I47: ='CSA 덤프 v1.0'!H47 -> (C). Instant Retire: Immediately retires a published article without requiring an approval | P47: Immediately retires a published article without requiring an approval.
A48: 47 | B48: =B47 -> 0 | C48: =C47 -> 7 | H48: ='CSA 덤프 v1.0'!G48 -> 보기 | I48: ='CSA 덤프 v1.0'!H48 -> (D). Retire Knowledge: Moves a knowledge article to the retired state.
A49: 48 | B49: =B48 -> 0 | C49: =C48 -> 7 | D49: a | H49: ='CSA 덤프 v1.0'!G49 -> 답 | I49: ='CSA 덤프 v1.0'!H49 -> A | J49: =IF(ISBLANK(D49),"",D49=$I49) -> TRUE | K49: =IF(ISBLANK(E49),"",E49=$I49) | L49: =IF(ISBLANK(F49),"",F49=$I49) | M49: =IF(ISBLANK(G49),"",G49=$I49) | N49: =COUNTIF(J49:M49,FALSE) -> 0 | P49: C도 정답인듯 하다
A50: 49 | B50: =B49 -> 0 | C50: =C49 -> 7 | H50: ='CSA 덤프 v1.0'!G50 -> 0 | I50: ='CSA 덤프 v1.0'!H50 -> 0
A51: 50 | B51: 0 | C51: 8 | H51: ='CSA 덤프 v1.0'!G51 -> 문제 | I51: ='CSA 덤프 v1.0'!H51 -> NO.8 Which statement is true about business rules?
A52: 51 | B52: =B51 -> 0 | C52: =C51 -> 8 | H52: ='CSA 덤프 v1.0'!G52 -> 보기 | I52: ='CSA 덤프 v1.0'!H52 -> (A). A business rule must run before a database action occurs
A53: 52 | B53: =B52 -> 0 | C53: =C52 -> 8 | H53: ='CSA 덤프 v1.0'!G53 -> 보기 | I53: ='CSA 덤프 v1.0'!H53 -> (B). A business rule can be a piece of Javascript
A54: 53 | B54: =B53 -> 0 | C54: =C53 -> 8 | H54: ='CSA 덤프 v1.0'!G54 -> 보기 | I54: ='CSA 덤프 v1.0'!H54 -> (C). A business rule must not run before a database action occurs
A55: 54 | B55: =B54 -> 0 | C55: =C54 -> 8 | H55: ='CSA 덤프 v1.0'!G55 -> 보기 | I55: ='CSA 덤프 v1.0'!H55 -> (D). A business rule monitors fields on a form
A56: 55 | B56: =B55 -> 0 | C56: =C55 -> 8 | D56: b | H56: ='CSA 덤프 v1.0'!G56 -> 답 | I56: ='CSA 덤프 v1.0'!H56 -> B | J56: =IF(ISBLANK(D56),"",D56=$I56) -> TRUE | K56: =IF(ISBLANK(E56),"",E56=$I56) | L56: =IF(ISBLANK(F56),"",F56=$I56) | M56: =IF(ISBLANK(G56),"",G56=$I56) | N56: =COUNTIF(J56:M56,FALSE) -> 0
A57: 56 | B57: =B56 -> 0 | C57: =C56 -> 8 | H57: ='CSA 덤프 v1.0'!G57 -> 0 | I57: ='CSA 덤프 v1.0'!H57 -> 0
A58: 57 | B58: 0 | C58: 9 | H58: ='CSA 덤프 v1.0'!G58 -> 문제 | I58: ='CSA 덤프 v1.0'!H58 -> NO.9 What is the purpose of the Event Registry?
A59: 58 | B59: =B58 -> 0 | C59: =C58 -> 9 | H59: ='CSA 덤프 v1.0'!G59 -> 보기 | I59: ='CSA 덤프 v1.0'!H59 -> (A). The Event Registry lists all Events that have successfully completed within a 24-hour period
A60: 59 | B60: =B59 -> 0 | C60: =C59 -> 9 | H60: ='CSA 덤프 v1.0'!G60 -> 보기 | I60: ='CSA 덤프 v1.0'!H60 -> (B). The Event Registry is a list of all Events that originate through an integration
A61: 60 | B61: =B60 -> 0 | C61: =C60 -> 9 | H61: ='CSA 덤프 v1.0'!G61 -> 보기 | I61: ='CSA 덤프 v1.0'!H61 -> (C). The Event Registry is a module that provides Event definitions
A62: 61 | B62: =B61 -> 0 | C62: =C61 -> 9 | H62: ='CSA 덤프 v1.0'!G62 -> 보기 | I62: ='CSA 덤프 v1.0'!H62 -> (D). The Event Registry is a list of all Events that have successfully completed after being Invoked by a script
A63: 62 | B63: =B62 -> 0 | C63: =C62 -> 9 | D63: c | H63: ='CSA 덤프 v1.0'!G63 -> 답 | I63: ='CSA 덤프 v1.0'!H63 -> C | J63: =IF(ISBLANK(D63),"",D63=$I63) -> TRUE | K63: =IF(ISBLANK(E63),"",E63=$I63) | L63: =IF(ISBLANK(F63),"",F63=$I63) | M63: =IF(ISBLANK(G63),"",G63=$I63) | N63: =COUNTIF(J63:M63,FALSE) -> 0
A64: 63 | B64: =B63 -> 0 | C64: =C63 -> 9 | H64: ='CSA 덤프 v1.0'!G64 -> 0 | I64: ='CSA 덤프 v1.0'!H64 -> 0
A65: 64 | B65: 0 | C65: 10 | H65: ='CSA 덤프 v1.0'!G65 -> 문제 | I65: ='CSA 덤프 v1.0'!H65 -> NO.10 What is the name of the conversational bot platform that provides assistance to help users obtain information, make decisions, and perform common tasks?
A66: 65 | B66: =B64 -> 0 | C66: =C64 -> 9 | H66: ='CSA 덤프 v1.0'!G66 -> 보기 | I66: ='CSA 덤프 v1.0'!H66 -> (A). Answer Agent
H67: ='CSA 덤프 v1.0'!G67 -> 0 | I67: ='CSA 덤프 v1.0'!H67 -> (B). Live Feed
H68: ='CSA 덤프 v1.0'!G68 -> 0 | I68: ='CSA 덤프 v1.0'!H68 -> (C). Virtual Agent
H69: ='CSA 덤프 v1.0'!G69 -> 0 | I69: ='CSA 덤프 v1.0'!H69 -> (D). Connect Chat
A70: 66 | B70: =B65 -> 0 | C70: =C65 -> 10 | D70: c | G70: ='CSA 덤프 v1.0'!G70 -> 답 | I70: ='CSA 덤프 v1.0'!H70 -> C | J70: =IF(ISBLANK(D70),"",D70=$I70) -> TRUE | K70: =IF(ISBLANK(E70),"",E70=$I70) | L70: =IF(ISBLANK(F70),"",F70=$I70) | M70: =IF(ISBLANK(#REF!),"",#REF!=$I70) -> #REF! | N70: =COUNTIF(J70:M70,FALSE) -> 0
A71: 67 | B71: =B66 -> 0 | C71: =C66 -> 9 | H71: ='CSA 덤프 v1.0'!G71 -> 0 | I71: ='CSA 덤프 v1.0'!H71 -> 0
A72: 68 | B72: 2 | C72: 11 | H72: ='CSA 덤프 v1.0'!G72 -> 문제 | I72: ='CSA 덤프 v1.0'!H72 -> NO.11 User records are stored in which table?
A73: 69 | B73: =B72 -> 2 | C73: =C72 -> 11 | H73: ='CSA 덤프 v1.0'!G73 -> 보기 | I73: ='CSA 덤프 v1.0'!H73 -> (A). User [sys_user]
A74: 70 | B74: =B73 -> 2 | C74: =C73 -> 11 | H74: ='CSA 덤프 v1.0'!G74 -> 보기 | I74: ='CSA 덤프 v1.0'!H74 -> (B). User [sn_user]
A75: 71 | B75: =B74 -> 2 | C75: =C74 -> 11 | H75: ='CSA 덤프 v1.0'!G75 -> 보기 | I75: ='CSA 덤프 v1.0'!H75 -> (C). User [u_sys_user]
A76: 72 | B76: =B75 -> 2 | C76: =C75 -> 11 | H76: ='CSA 덤프 v1.0'!G76 -> 보기 | I76: ='CSA 덤프 v1.0'!H76 -> (D). User [s_user]
A77: 73 | B77: =B76 -> 2 | C77: =C76 -> 11 | D77: a | H77: ='CSA 덤프 v1.0'!G77 -> 답 | I77: ='CSA 덤프 v1.0'!H77 -> A | J77: =IF(ISBLANK(D77),"",D77=$I77) -> TRUE | K77: =IF(ISBLANK(E77),"",E77=$I77) | L77: =IF(ISBLANK(F77),"",F77=$I77) | M77: =IF(ISBLANK(G77),"",G77=$I77) | N77: =COUNTIF(J77:M77,FALSE) -> 0
A78: 74 | B78: =B77 -> 2 | C78: =C77 -> 11 | H78: ='CSA 덤프 v1.0'!G78 -> 0 | I78: ='CSA 덤프 v1.0'!H78 -> 0
A79: 75 | B79: 0 | C79: 12 | H79: ='CSA 덤프 v1.0'!G79 -> 문제 | I79: ='CSA 덤프 v1.0'!H79 -> NO.12 Which tool should be used to populate commonly used fields in a form?
A80: 76 | B80: =B79 -> 0 | C80: =C79 -> 12 | H80: ='CSA 덤프 v1.0'!G80 -> 보기 | I80: ='CSA 덤프 v1.0'!H80 -> (A). Template | P80: populate : 채우다
A81: 77 | B81: =B80 -> 0 | C81: =C80 -> 12 | H81: ='CSA 덤프 v1.0'!G81 -> 보기 | I81: ='CSA 덤프 v1.0'!H81 -> (B). Reference Qualifier
A82: 78 | B82: =B81 -> 0 | C82: =C81 -> 12 | H82: ='CSA 덤프 v1.0'!G82 -> 보기 | I82: ='CSA 덤프 v1.0'!H82 -> (C). Formatter
A83: 79 | B83: =B82 -> 0 | C83: =C82 -> 12 | H83: ='CSA 덤프 v1.0'!G83 -> 보기 | I83: ='CSA 덤프 v1.0'!H83 -> (D). Assignment Rule
A84: 80 | B84: =B83 -> 0 | C84: =C83 -> 12 | D84: a | H84: ='CSA 덤프 v1.0'!G84 -> 답 | I84: ='CSA 덤프 v1.0'!H84 -> A | J84: =IF(ISBLANK(D84),"",D84=$I84) -> TRUE | K84: =IF(ISBLANK(E84),"",E84=$I84) | L84: =IF(ISBLANK(F84),"",F84=$I84) | M84: =IF(ISBLANK(G84),"",G84=$I84) | N84: =COUNTIF(J84:M84,FALSE) -> 0
A85: 81 | B85: =B84 -> 0 | C85: =C84 -> 12 | H85: ='CSA 덤프 v1.0'!G85 -> 0 | I85: ='CSA 덤프 v1.0'!H85 -> 0
A86: 82 | B86: 0 | C86: 13 | H86: ='CSA 덤프 v1.0'!G86 -> 문제 | I86: ='CSA 덤프 v1.0'!H86 -> NO.13 Which one of the following statements describes a characteristic of role assignment?
A87: 83 | B87: =B86 -> 0 | C87: =C86 -> 13 | H87: ='CSA 덤프 v1.0'!G87 -> 보기 | I87: ='CSA 덤프 v1.0'!H87 -> (A). Roles can contain other roles, when you are assigned a role, you inherit all the roles within that role
A88: 84 | B88: =B87 -> 0 | C88: =C87 -> 13 | H88: ='CSA 덤프 v1.0'!G88 -> 보기 | I88: ='CSA 덤프 v1.0'!H88 -> (B). Users can click on the Personalize Role feature to try different roles
A89: 85 | B89: =B88 -> 0 | C89: =C88 -> 13 | H89: ='CSA 덤프 v1.0'!G89 -> 보기 | I89: ='CSA 덤프 v1.0'!H89 -> (C). A role is granted to a user by the System Administrator
A90: 86 | B90: =B89 -> 0 | C90: =C89 -> 13 | H90: ='CSA 덤프 v1.0'!G90 -> 보기 | I90: ='CSA 덤프 v1.0'!H90 -> (D). Each user has a role in the ServiceNow platform
A91: 87 | B91: =B90 -> 0 | C91: =C90 -> 13 | D91: a | H91: ='CSA 덤프 v1.0'!G91 -> 답 | I91: ='CSA 덤프 v1.0'!H91 -> A | J91: =IF(ISBLANK(D91),"",D91=$I91) -> TRUE | K91: =IF(ISBLANK(E91),"",E91=$I91) | L91: =IF(ISBLANK(F91),"",F91=$I91) | M91: =IF(ISBLANK(G91),"",G91=$I91) | N91: =COUNTIF(J91:M91,FALSE) -> 0
A92: 88 | B92: =B91 -> 0 | C92: =C91 -> 13 | H92: ='CSA 덤프 v1.0'!G92 -> 0 | I92: ='CSA 덤프 v1.0'!H92 -> 0
A93: 89 | B93: 0 | C93: 14 | H93: ='CSA 덤프 v1.0'!G93 -> 문제 | I93: ='CSA 덤프 v1.0'!H93 -> NO.14 When does the Submit button appear on a form?
A94: 90 | B94: =B93 -> 0 | C94: =C93 -> 14 | H94: ='CSA 덤프 v1.0'!G94 -> 보기 | I94: ='CSA 덤프 v1.0'!H94 -> (A). When saving an old record
A95: 91 | B95: =B94 -> 0 | C95: =C94 -> 14 | H95: ='CSA 덤프 v1.0'!G95 -> 보기 | I95: ='CSA 덤프 v1.0'!H95 -> (B). When creating a new record
A96: 92 | B96: =B95 -> 0 | C96: =C95 -> 14 | H96: ='CSA 덤프 v1.0'!G96 -> 보기 | I96: ='CSA 덤프 v1.0'!H96 -> (C). When changing the reference field in an existing record
A97: 93 | B97: =B96 -> 0 | C97: =C96 -> 14 | H97: ='CSA 덤프 v1.0'!G97 -> 보기 | I97: ='CSA 덤프 v1.0'!H97 -> (D). When updating an existing record
A98: 94 | B98: =B97 -> 0 | C98: =C97 -> 14 | D98: b | H98: ='CSA 덤프 v1.0'!G98 -> 답 | I98: ='CSA 덤프 v1.0'!H98 -> B | J98: =IF(ISBLANK(D98),"",D98=$I98) -> TRUE | K98: =IF(ISBLANK(E98),"",E98=$I98) | L98: =IF(ISBLANK(F98),"",F98=$I98) | M98: =IF(ISBLANK(G98),"",G98=$I98) | N98: =COUNTIF(J98:M98,FALSE) -> 0
A99: 95 | B99: =B98 -> 0 | C99: =C98 -> 14 | H99: ='CSA 덤프 v1.0'!G99 -> 0 | I99: ='CSA 덤프 v1.0'!H99 -> 0
A100: 96 | B100: 0 | C100: 15 | H100: ='CSA 덤프 v1.0'!G100 -> 문제 | I100: ='CSA 덤프 v1.0'!H100 -> NO.15 Which tool is used to define relationships between fields in an import set table and a target table?
...

Sheet 그 외 기출내용
A1: Field란 무엇인가
A2: 설명 주고 정답 Catalog Builder이였던듯?
A3: Knowledge Article 모두 볼 수 있게 하는거 All View Setting 어쩌고
A4: Knowledge Article 권한 설정 Team, Department, Group
A5: 유저 정보 바꾸려면 뭐 눌러야하냐 Gear, Magnifier
A6: UI Policy 뭐 있냐(3개) View links, View Buttons, View 어쩌고 등
A7: 업데이트 했을때 notification가게 하려면 administrator가 뭐 해야하냐
A8: High Security Setting하려면 뭐해야하냐 ? Elevate Role 함
A9: table 관계 설명주고 Base table이랑 parent child 구분
A10: Group 정의, Role 정의
A11: Core 테이블과 Parent 테이블 비교
A12: https://quizlet.com/662858700/csa-2022-flash-cards/
